uploadthing_py/__init__.py
uploadthing_py/builder.py
uploadthing_py/py.typed
uploadthing_py/request_handler.py
uploadthing_py/types.py
uploadthing_py/utapi.py
uploadthing_py/utils.py
uploadthing_py-0.3.3.dist-info/METADATA
uploadthing_py-0.3.3.dist-info/WHEEL
uploadthing_py-0.3.3.dist-info/RECORD
